pipra/__init__.py
pipra/floodfill.py
pipra/grabcut.py
pipra/pipra.py
pipra-0.3.4.dist-info/LICENSE
pipra-0.3.4.dist-info/METADATA
pipra-0.3.4.dist-info/WHEEL
pipra-0.3.4.dist-info/entry_points.txt
pipra-0.3.4.dist-info/top_level.txt
pipra-0.3.4.dist-info/RECORD
