Metadata-Version: 2.1
Name: pipra
Version: 0.3.4
Summary: An annotation tool to allow binary px-based labels.
Home-page: UNKNOWN
Author: Andreas M Kist
Author-email: andreas.kist@fau.de
License: GPLv3
Project-URL: Source, https://github.com/anki-xyz/pipra
Project-URL: Tracker, https://github.com/anki-xyz/pipra/issues
Keywords: annotation,labelling
Platform: UNKNOWN
Classifier: Development Status :: 4 - Beta
Classifier: Intended Audience :: Science/Research
Classifier: License :: OSI Approved :: GNU General Public License v3 or later (GPLv3+)
Classifier: Programming Language :: Python :: 3.6
Classifier: Programming Language :: Python :: 3.7
Classifier: Programming Language :: Python :: 3.8
Requires-Dist: pyqtgraph (>=0.10.0)
Requires-Dist: numpy
Requires-Dist: numba
Requires-Dist: flammkuchen
Requires-Dist: pyqt5
Requires-Dist: scikit-image
Requires-Dist: imageio
Requires-Dist: imageio-ffmpeg
Requires-Dist: opencv-python
